Mensajes/__init__.py
Mensajes/adios/__init__.py
Mensajes/adios/despedidas.py
Mensajes/hola/__init__.py
Mensajes/hola/saludos.py
tests/__init__.py
tests/test_hola.py
mensajes_diegom-6.0.dist-info/LICENSE
mensajes_diegom-6.0.dist-info/METADATA
mensajes_diegom-6.0.dist-info/WHEEL
mensajes_diegom-6.0.dist-info/top_level.txt
mensajes_diegom-6.0.dist-info/RECORD
